{
    "id": "5483",
    "name": "刘苏",
    "desc": "刘苏",
    "icon_url": "https://uploadstatic.mihoyo.com/ys-obc/2022/12/06/158741257/2d2a294488e6a5ecff2af216d1a4a81c_717991606526394346.png",
    "base_info": {
        "name": "刘苏",
        "common_img": "https://uploadstatic.mihoyo.com/ys-obc/2022/12/06/158741257/2d2a294488e6a5ecff2af216d1a4a81c_2786433729730992349.png",
        "gold_img": "https://uploadstatic.mihoyo.com/ys-obc/2022/12/04/158741257/38727e33a0814864b1318b07e07c7f54_8454656797332983005.gif",
        "life": 1,
        "life_bg": 9,
        "energy": 0,
        "energy_bg": 0,
        "element": [],
        "weapon": [],
        "faction": [],
        "energy_count": [],
        "acquisition": [
            "卡牌商店购买、完成挑战目标"
        ],
        "card_type": [
            "支援牌"
        ],
        "tags": [
            "伙伴"
        ],
        "cost": [
            "1"
        ]
    },
    "skills": [],
    "summons": [],
    "effect": {
        "rich_text": "<p style=\"white-space: pre-wrap;\">我方切换角色后：如果切换到的角色没有<strong><u>充能</u></strong><span data-type=\"详情\" data-name=\"&lt;p style=&#34;white-space: pre-wrap;&#34;&gt;角色使用「元素爆发」时，需要消耗充能。&lt;/p&gt;&lt;p style=&#34;white-space: pre-wrap;&#34;&gt;角色使用「元素战技」或「普通攻击」后，会获得1点充能。&lt;/p&gt;&lt;p style=&#34;white-space: pre-wrap; min-height: 1.5em;&#34;&gt;&lt;/p&gt;\" class=\"wiki-note-text\"><sup class=\"wiki-sup\">[详情]</sup></span>，则使该角色获得1点充能。(每回合1次)<br/><strong><u>可用次数</u></strong><span data-type=\"详情\" data-name=\"&lt;p style=&#34;white-space: pre-wrap;&#34;&gt;此牌效果触发后，会消耗1次可用次数；&lt;/p&gt;&lt;p style=&#34;white-space: pre-wrap;&#34;&gt;可用次数耗尽后，立刻弃置此牌。&lt;/p&gt;&lt;p style=&#34;white-space: pre-wrap; min-height: 1.5em;&#34;&gt;&lt;/p&gt;\" class=\"wiki-note-text\"><sup class=\"wiki-sup\">[详情]</sup></span>：2</p>"
    },
    "story": {
        "rich_text": "<p style=\"white-space: pre-wrap;\"><strong>且听下回·刘苏</strong></p><p style=\"white-space: pre-wrap;\">「各位客官,接下来您们还想再听段什么？」</p>"
    }
}
